{
    "Logger ID": 3,
    "Cell ID": 3121,
    "Upload Method": "LoRa",
    "Days": 3,
    "Hours": 0,
    "Minutes": 0,
    "Seconds": 0,
    "Enabled Sensors": {
        "Voltage": true,
        "Current": false,
        "Teros12": false,
        "Teros21": false,
        "BME280": false
    },
    "Calibration V Slope": 3.0,
    "Calibration V Offset": 3.0,
    "Calibration I Slope": 3.0,
    "Calibration I Offset": 3.0,
    "WiFi SSID": "",
    "WiFi Password": "",
    "API Endpoint URL": "",
    "API Port": 0
}